sparkql/__init__.py
sparkql/accessors.py
sparkql/exceptions.py
sparkql/fields/__init__.py
sparkql/fields/array.py
sparkql/fields/atomic.py
sparkql/fields/base.py
sparkql/fields/struct.py
sparkql/formatters.py
sparkql/py.typed
sparkql/schema_builder.py
sparkql/schema_merger.py
sparkql-0.9.0.dist-info/entry_points.txt
sparkql-0.9.0.dist-info/LICENSE
sparkql-0.9.0.dist-info/WHEEL
sparkql-0.9.0.dist-info/METADATA
sparkql-0.9.0.dist-info/RECORD
