Metadata-Version: 2.1
Name: sparkql
Version: 0.9.0
Summary: sparkql: Apache Spark SQL DataFrame schema management for sensible humans
Home-page: https://github.com/mattjw/sparkql
License: MIT
Author: Matt J Williams
Author-email: mattjw@mattjw.net
Requires-Python: >=3.7.2,<4.0.0
Classifier: License :: OSI Approved :: MIT License
Classifier: Programming Language :: Python :: 3
Classifier: Programming Language :: Python :: 3.8
Classifier: Programming Language :: Python :: 3.9
Classifier: Programming Language :: Python :: 3.10
Classifier: Programming Language :: Python :: 3.11
Requires-Dist: pyspark (>=3.0,<4.0)
Project-URL: Repository, https://github.com/mattjw/sparkql
